CHANGES.rst
LICENSE
MANIFEST.in
README.rst
setup.cfg
setup.py
aiokafka_commit/__init__.py
aiokafka_commit/abc.py
aiokafka_commit/admin.py
aiokafka_commit/client.py
aiokafka_commit/cluster.py
aiokafka_commit/conn.py
aiokafka_commit/errors.py
aiokafka_commit/helpers.py
aiokafka_commit/structs.py
aiokafka_commit/util.py
aiokafka_commit/record/_crecords/crc32c.c
aiokafka_commit_commit.egg-info/PKG-INFO
aiokafka_commit_commit.egg-info/SOURCES.txt
aiokafka_commit_commit.egg-info/dependency_links.txt
aiokafka_commit_commit.egg-info/requires.txt
aiokafka_commit_commit.egg-info/top_level.txt