Metadata-Version: 2.1
Name: aiokafka-commit-commit
Version: 0.0.3
Summary: Kafka integration with asyncio.
Home-page: http://aiokafka.readthedocs.org
Author: Artiom
Author-email: art.israel.mail@gmail.com
License: Apache 2
Download-URL: https://github.com/Arti0m/aiokafka
Project-URL: Source, https://github.com/Arti0m/aiokafka
Platform: POSIX
Classifier: License :: OSI Approved :: Apache Software License
Classifier: Intended Audience :: Developers
Classifier: Programming Language :: Python :: 3
Classifier: Programming Language :: Python :: 3.7
Classifier: Programming Language :: Python :: 3.8
Classifier: Programming Language :: Python :: 3.9
Classifier: Programming Language :: Python :: 3.10
Classifier: Programming Language :: Python :: 3.11
Classifier: Operating System :: OS Independent
Classifier: Topic :: System :: Networking
Classifier: Topic :: System :: Distributed Computing
Classifier: Framework :: AsyncIO
Classifier: Development Status :: 4 - Beta
Requires-Python: >=3.10
Provides-Extra: snappy
Provides-Extra: lz4
Provides-Extra: zstd
Provides-Extra: gssapi
Provides-Extra: all
License-File: LICENSE
